{
    "ac_deg": "專科", 
    "ac_dep": "護理學系", 
    "ac_sch": "無", 
    "com_addr": "新竹縣湖口鄉千湖路38巷20號", 
    "com_name": "新竹縣私立竹光長期照顧中心(養護型)", 
    "com_unicode": "30171206", 
    "doom": "提供住宿，月扣金額2500", 
    "extra_hrs": "依工作需要", 
    "food": "無", 
    "hire_dur": "不定期契約", 
    "hire_num": "2", 
    "job_desc": "1.管路照護2.生活照護3.疾病照顧", 
    "job_id": "8210281", 
    "job_req": "兼職\r\n                            \r\n                            日班：自08時00分至17時00分、夜班：自04時00分至00時00分、部份工時：自00時00分至08時00分", 
    "job_title": "護士", 
    "job_type": "護士", 
    "off_days": "依公司規定(輪班排班假，目前有三位護理人員。)", 
    "pay_type": "月薪\r\n                            \r\n                            32000 - 34000", 
    "work_exp": "需具備「護士執照」，1年內工作經驗", 
    "work_loc": "工作地非屬專區"
}