{
    "ac_deg": "大學", 
    "ac_dep": "英美語文學系,企業管理學類", 
    "ac_sch": "無", 
    "com_addr": "高雄市左營區菜公里重立路４３７號１樓", 
    "com_name": "奇貿股份有限公司", 
    "com_unicode": "86039530", 
    "doom": "不提供住宿", 
    "extra_hrs": "依工作需要", 
    "food": "", 
    "hire_dur": "不定期契約", 
    "hire_num": "1", 
    "job_desc": "徵:國外業務(具扣件產業相關經驗佳) (*負責國內外業務 a.國外客戶詢價/報價/訂單(開發客戶及年度參展)b.聯絡國內廠商.安排.生產.出貨等流程c.負責與國外客戶業務聯繫d.ISO 檔案文件管理其他條件:1.五年以上實際外銷業務經驗者2.外文系畢業尤佳3.需附英文履歷。) 意者請MAIL履歷，合者約面試時間", 
    "job_id": "8596987", 
    "job_req": "全職\r\n                            \r\n                            日班：自08時30分至18時00分", 
    "job_title": "國外業務 (具扣件產業相關經驗佳)", 
    "job_type": "國貿人員", 
    "off_days": "週休二日", 
    "pay_type": "依學經歷、證照核薪", 
    "work_exp": "3年以上工作經驗", 
    "work_loc": "工作地非屬專區"
}