{
    "ac_deg": "專科", 
    "ac_dep": "一般商業學類", 
    "ac_sch": "無", 
    "com_addr": "新北市三重區中正北路176巷16號1樓", 
    "com_name": "久峰農業科技行銷股份有限公司", 
    "com_unicode": "66434267", 
    "doom": "不提供住宿", 
    "extra_hrs": "偶爾", 
    "food": "無", 
    "hire_dur": "不定期契約", 
    "hire_num": "1", 
    "job_desc": "協助會計主管辦理會計及財務處理的行政相關事務。", 
    "job_id": "8605419", 
    "job_req": "全職\r\n                            \r\n                            日班：自09時00分至18時30分", 
    "job_title": "會計助理", 
    "job_type": "會計助理", 
    "off_days": "週休二日", 
    "pay_type": "月薪\r\n                            \r\n                            25000 - 27000", 
    "work_exp": "不拘", 
    "work_loc": "工作地非屬專區"
}