{
    "ac_deg": "不拘", 
    "ac_dep": "不拘", 
    "ac_sch": "無", 
    "com_addr": "桃園市大園區航勤南路６號", 
    "com_name": "華夏航科國際股份有限公司", 
    "com_unicode": "23361835", 
    "doom": "不提供住宿", 
    "extra_hrs": "", 
    "food": "", 
    "hire_dur": "不定期契約", 
    "hire_num": "4", 
    "job_desc": "清洗飛機外部/應徵結果將如實回報，無誠勿試", 
    "job_id": "8639123", 
    "job_req": "全職\r\n                            \r\n                            夜班：自22時30分至06時30分", 
    "job_title": "飛機外觀清潔員", 
    "job_type": "其他產品維修人員", 
    "off_days": "排休(1個月休8日)", 
    "pay_type": "月薪\r\n                            \r\n                            32000 - 38000", 
    "work_exp": "不拘", 
    "work_loc": "工作地非屬專區"
}