{
    "ac_deg": "不拘", 
    "ac_dep": "不拘", 
    "ac_sch": "無", 
    "com_addr": "高雄市梓官區和平路60號", 
    "com_name": "垣田景觀設計開發有限公司", 
    "com_unicode": "53253290", 
    "doom": "不提供住宿", 
    "extra_hrs": "依工作需要", 
    "food": "無", 
    "hire_dur": "不定期契約", 
    "hire_num": "1", 
    "job_desc": "本公司從事公園、學校及庭園景觀施工及維護工作徵:園藝技術員(工作時間:08:00-17:00，意者請電洽。)，具庭園施工維護等工地工程經驗、樹木草花種植、水車澆水、樹木、草皮修剪等，具相關工作經驗及小貨車駕照者佳。", 
    "job_id": "8651655", 
    "job_req": "全職\r\n                            \r\n                            日班：自08時00分至17時00分", 
    "job_title": "園藝工程技術員", 
    "job_type": "園藝栽培工", 
    "off_days": "週休二日", 
    "pay_type": "月薪\r\n                            \r\n                            26000 - 34000", 
    "work_exp": "不拘", 
    "work_loc": "工作地非屬專區"
}