{
    "ac_deg": "高職", 
    "ac_dep": "電子工程(學)系", 
    "ac_sch": "無", 
    "com_addr": "高雄市前鎮區高雄加工出口區東九街2之3號 (高雄加工出口區)", 
    "com_name": "瑩慶光電有限公司", 
    "com_unicode": "97137220", 
    "doom": "不提供住宿", 
    "extra_hrs": "依工作需要", 
    "food": "", 
    "hire_dur": "不定期契約", 
    "hire_num": "5", 
    "job_desc": "徵：短期作業員1.生產線作業人員。 2.零組件/面板檢測。 3.主管交辦事項。", 
    "job_id": "8652573", 
    "job_req": "全職\r\n                            \r\n                            日班：自08時00分至17時00分", 
    "job_title": "短期作業員", 
    "job_type": "電子設備組裝作業員", 
    "off_days": "週休二日", 
    "pay_type": "月薪\r\n                            \r\n                            22000 - 22000", 
    "work_exp": "需具備「有液晶顯示器檢查經驗」，1年以上工作經驗", 
    "work_loc": "工作地非屬專區"
}