{
    "ac_deg": "不拘", 
    "ac_dep": "不拘", 
    "ac_sch": "無", 
    "com_addr": "新北市新店區民權路42巷59弄5號(近大坪林捷運站1號出口3分鐘既到)", 
    "com_name": "宏騏興業有限公司", 
    "com_unicode": "12837166", 
    "doom": "不提供住宿", 
    "extra_hrs": "不需加班", 
    "food": "無", 
    "hire_dur": "不定期契約", 
    "hire_num": "1", 
    "job_desc": "基本電腦能力、網拍、基本行政事務工作內容：網拍處理、資料輸入、圖片上傳。 環境：小公司、人事單純，全員無抽菸喝酒等不良習慣", 
    "job_id": "8568011", 
    "job_req": "全職\r\n                            \r\n                            日班：自08時30分至17時30分", 
    "job_title": "電腦行政", 
    "job_type": "電腦操作及輸入(Key in)人員", 
    "off_days": "週休二日", 
    "pay_type": "月薪\r\n                            \r\n                            24000 - 26000", 
    "work_exp": "不拘", 
    "work_loc": "工作地非屬專區"
}