{
    "ac_deg": "不拘", 
    "ac_dep": "不拘", 
    "ac_sch": "無", 
    "com_addr": "新竹市新竹市經國路二段１號", 
    "com_name": "昇冠加油站股份有限公司", 
    "com_unicode": "70599732", 
    "doom": "不提供住宿", 
    "extra_hrs": "依工作需要", 
    "food": "提供1餐，每餐扣款金額", 
    "hire_dur": "不定期契約", 
    "hire_num": "2", 
    "job_desc": "加油服務、收銀及洗車；工作時間:(早班)06:30--14:30、(中班)14:30-22:30、(夜班)22:30-06:30；固定三班制；月排休8日。", 
    "job_id": "8578201", 
    "job_req": "全職\r\n                            \r\n                            日班：自06時30分至14時30分、中班：自14時30分至22時30分、夜班：自22時30分至06時30分、輪班三班制", 
    "job_title": "加油服務員(職場學習及再適應計畫)107/11/8止", 
    "job_type": "加油服務生", 
    "off_days": "排休(1個月休8日)", 
    "pay_type": "月薪\r\n                            \r\n                            22000 - 24000", 
    "work_exp": "不拘", 
    "work_loc": "工作地非屬專區"
}