{
    "ac_deg": "不拘", 
    "ac_dep": "不拘", 
    "ac_sch": "無", 
    "com_addr": "新竹市中華路六段２９５號", 
    "com_name": "良維汽車有限公司", 
    "com_unicode": "42743546", 
    "doom": "不提供住宿", 
    "extra_hrs": "", 
    "food": "提供1餐，每餐扣款金額", 
    "hire_dur": "不定期契約", 
    "hire_num": "1", 
    "job_desc": "拆卸中古車的零件相關工作", 
    "job_id": "8579957", 
    "job_req": "全職\r\n                            \r\n                            日班：自09時00分至18時00分", 
    "job_title": "汽車零件拆卸員", 
    "job_type": "其它機械操作工", 
    "off_days": "依公司規定(.)", 
    "pay_type": "月薪\r\n                            \r\n                            30000 - 40000", 
    "work_exp": "不拘", 
    "work_loc": "工作地非屬專區"
}