{
    "ac_deg": "不拘", 
    "ac_dep": "不拘", 
    "ac_sch": "無", 
    "com_addr": "新北市瑞芳區頂坪路瑞芳工業區２４號", 
    "com_name": "瑞紳產品開發有限公司", 
    "com_unicode": "54757805", 
    "doom": "不提供住宿", 
    "extra_hrs": "", 
    "food": "", 
    "hire_dur": "不定期契約", 
    "hire_num": "1", 
    "job_desc": "鐵工 需會焊接", 
    "job_id": "8582421", 
    "job_req": "全職\r\n                            \r\n                            日班：自08時00分至17時00分", 
    "job_title": "其它機械操作工", 
    "job_type": "其它機械操作工", 
    "off_days": "週休二日", 
    "pay_type": "依學經歷、證照核薪", 
    "work_exp": "不拘", 
    "work_loc": "工作地非屬專區"
}