{
    "ac_deg": "大學", 
    "ac_dep": "英文學系", 
    "ac_sch": "無", 
    "com_addr": "高雄市左營區華夏路３２９號２Ｆ", 
    "com_name": "高雄市私立成峰外語文理短期補習班", 
    "com_unicode": "47638375", 
    "doom": "不提供住宿", 
    "extra_hrs": "", 
    "food": "", 
    "hire_dur": "不定期契約", 
    "hire_num": "1", 
    "job_desc": "徵：行政人員 (教英文系畢業尤佳，需有2年以上工作經驗，電話接聽，櫃台接待，需結算薪資,要有出納概念，月薪26000~30000元。日班/晚班，13:30~21:30) 意者請郵寄履歷至redbootsue@gmail.com 蘇經理收 ※請註明應徵職務", 
    "job_id": "8584173", 
    "job_req": "全職\r\n                            \r\n                            日班、中班", 
    "job_title": "行政人員", 
    "job_type": "行政助理", 
    "off_days": "週休二日", 
    "pay_type": "月薪\r\n                            \r\n                            26000 - 30000", 
    "work_exp": "不拘", 
    "work_loc": "工作地非屬專區"
}