{
    "ac_deg": "專科", 
    "ac_dep": "不拘", 
    "ac_sch": "無", 
    "com_addr": "高雄市楠梓區楠梓西巷21弄3號", 
    "com_name": "高雄市私立高竿升學文理短期補習班", 
    "com_unicode": "92078145", 
    "doom": "不提供住宿", 
    "extra_hrs": "依工作需要", 
    "food": "", 
    "hire_dur": "不定期契約", 
    "hire_num": "1", 
    "job_desc": "徵:行政櫃台-接待家長、介紹相關課程，負責一般文書資料處理工作，維護、更新、管理各類文件檔案，完成主管交代之事宜，意者親洽。", 
    "job_id": "8585893", 
    "job_req": "全職\r\n                            \r\n                            日班：自14時00分至22時00分", 
    "job_title": "行政櫃枱", 
    "job_type": "行政總務人員", 
    "off_days": "週休二日", 
    "pay_type": "依學經歷、證照核薪", 
    "work_exp": "不拘", 
    "work_loc": "工作地非屬專區"
}