{
    "ac_deg": "大學", 
    "ac_dep": "不拘", 
    "ac_sch": "無", 
    "com_addr": "新北市五股區.", 
    "com_name": "台灣檢驗科技股份有限公司", 
    "com_unicode": "23928467", 
    "doom": "不提供住宿", 
    "extra_hrs": "", 
    "food": "", 
    "hire_dur": "不定期契約", 
    "hire_num": "1", 
    "job_desc": "1. 電子及電器、石油化學品、礦產材料、保健食品、化妝品等產品之化學測試、成份化驗分析2. 研讀各檢測方法及法規更新狀況", 
    "job_id": "8600007", 
    "job_req": "全職\r\n                            \r\n                            日班：自08時30分至17時30分", 
    "job_title": "有機化學分析師", 
    "job_type": "品管檢驗人員", 
    "off_days": "週休二日", 
    "pay_type": "依學經歷、證照核薪", 
    "work_exp": "不拘", 
    "work_loc": "工作地非屬專區"
}