{
    "ac_deg": "不拘", 
    "ac_dep": "不拘", 
    "ac_sch": "無", 
    "com_addr": "高雄市仁武區竹工三巷４０號", 
    "com_name": "順發鐵氟龍股份有限公司", 
    "com_unicode": "06721259", 
    "doom": "不提供住宿", 
    "extra_hrs": "", 
    "food": "", 
    "hire_dur": "不定期契約", 
    "hire_num": "2", 
    "job_desc": "徵:品管人員，須使用游標卡尺，日班，應徵者請電洽約面試時間", 
    "job_id": "8615793", 
    "job_req": "全職\r\n                            \r\n                            日班：自08時00分至17時30分", 
    "job_title": "品管人員", 
    "job_type": "品管檢驗人員", 
    "off_days": "週休二日", 
    "pay_type": "依學經歷、證照核薪", 
    "work_exp": "不拘", 
    "work_loc": "工作地非屬專區"
}