{
    "ac_deg": "不拘", 
    "ac_dep": "不拘", 
    "ac_sch": "無", 
    "com_addr": "台北市中山區南京西路16號B1", 
    "com_name": "宏佶企業社", 
    "com_unicode": "42252858", 
    "doom": "不提供住宿", 
    "extra_hrs": "", 
    "food": "", 
    "hire_dur": "不定期契約", 
    "hire_num": "10", 
    "job_desc": "門市業務，收銀及補貨管理", 
    "job_id": "8616609", 
    "job_req": "兼職\r\n                            \r\n                            日班：自07時00分至15時00分、夜班：自15時00分至23時00分、部份工時：自15時00分至23時00分、自18時00分至23時00分", 
    "job_title": "門市人員(便利商店)", 
    "job_type": "賣場（人員／儲備幹部）", 
    "off_days": "依公司規定(排休)", 
    "pay_type": "時薪\r\n                            \r\n                            140 - 150", 
    "work_exp": "不拘", 
    "work_loc": "工作地非屬專區"
}