{
    "ac_deg": "高中", 
    "ac_dep": "不拘", 
    "ac_sch": "無", 
    "com_addr": "新竹縣竹東鎮榮華里朝陽路７５號２樓", 
    "com_name": "奕宏房屋仲介有限公司(永慶不動產竹東朝陽加盟店)", 
    "com_unicode": "24222278", 
    "doom": "不提供住宿", 
    "extra_hrs": "依工作需要", 
    "food": "", 
    "hire_dur": "不定期契約", 
    "hire_num": "5", 
    "job_desc": "不動產業務仲介代銷(需具備不動產營業員證照)", 
    "job_id": "8617911", 
    "job_req": "全職\r\n                            \r\n                            日班：自09時00分至18時00分", 
    "job_title": "不動產業務人員", 
    "job_type": "不動產銷售人員", 
    "off_days": "依公司規定(依公司規定)", 
    "pay_type": "依學經歷、證照核薪", 
    "work_exp": "不拘", 
    "work_loc": "工作地非屬專區"
}