{
    "ac_deg": "專科", 
    "ac_dep": "電機工程(學)系", 
    "ac_sch": "無", 
    "com_addr": "台北市南港區南港路三段５２號５樓(意者請投履歷，合者通知面試)", 
    "com_name": "新鼎系統股份有限公司", 
    "com_unicode": "22619999", 
    "doom": "不提供住宿", 
    "extra_hrs": "依工作需要", 
    "food": "", 
    "hire_dur": "不定期契約", 
    "hire_num": "3", 
    "job_desc": "1.石化及其他工業之工廠控制系統的規劃設計工作2.控制系統(DCS)/可程式控制器(PLC)/人機介面(HMI)等系統規劃設計3.控制邏輯、控制策略、機電整合之規劃設計4.控制系統程式或資料庫規劃及應用5.參與整廠儀控系統現場測試與試俥調校工作意者請投履歷，合者通知面試0730-0900 彈性上下班，每班8小時依需求指派(臺北、桃園、台中、高雄)", 
    "job_id": "8620469", 
    "job_req": "全職\r\n                            \r\n                            日班", 
    "job_title": "PLC程式開發/機電整合工程師工程師", 
    "job_type": "機電整合工程師", 
    "off_days": "週休二日", 
    "pay_type": "月薪\r\n                            \r\n                            36000 - 36000", 
    "work_exp": "不拘", 
    "work_loc": "工作地非屬專區"
}