{
    "ac_deg": "不拘", 
    "ac_dep": "不拘", 
    "ac_sch": "無", 
    "com_addr": "台南市官田區南廍里三結義38號", 
    "com_name": "嵊家企業有限公司", 
    "com_unicode": "36290101", 
    "doom": "不提供住宿", 
    "extra_hrs": "依工作需要", 
    "food": "提供1餐，每餐扣款金額0", 
    "hire_dur": "不定期契約", 
    "hire_num": "2", 
    "job_desc": "1.機器配線，組裝機器，協助現場機械操作2.搬運貨物並協助出貨**不具經驗亦可，願意學習", 
    "job_id": "8620687", 
    "job_req": "全職\r\n                            \r\n                            日班：自07時45分至16時45分", 
    "job_title": "金屬組裝工", 
    "job_type": "機械組裝工", 
    "off_days": "週休二日", 
    "pay_type": "月薪\r\n                            \r\n                            25000 - 28000", 
    "work_exp": "不拘", 
    "work_loc": "工作地非屬專區"
}