{
    "ac_deg": "專科", 
    "ac_dep": "其他(機械工程學類, 電機工程學類, 電子工程學類, 光電工程學類, 資訊工程學類)", 
    "ac_sch": "無", 
    "com_addr": "新竹縣湖口鄉新竹工業區", 
    "com_name": "恩茂科技股份有限公司", 
    "com_unicode": "80701996", 
    "doom": "不提供住宿", 
    "extra_hrs": "", 
    "food": "", 
    "hire_dur": "不定期契約", 
    "hire_num": "1", 
    "job_desc": "1.客製化設備開發。 2.影像色彩處理。 3.自動調校系統維護開發。附加條件：具電子/電機 或 光電產業 之經驗 3 年以上 者佳", 
    "job_id": "8622089", 
    "job_req": "全職\r\n                            \r\n                            日班", 
    "job_title": "工程師-湖口-DJ-2457", 
    "job_type": "機械工程師", 
    "off_days": "週休二日", 
    "pay_type": "依學經歷、證照核薪", 
    "work_exp": "3年以上工作經驗", 
    "work_loc": "新竹工業區"
}