{
    "ac_deg": "高職", 
    "ac_dep": "不拘", 
    "ac_sch": "無", 
    "com_addr": "台中市烏日區五光路復光二巷32號", 
    "com_name": "臺灣三嵩工業有限公司", 
    "com_unicode": "52308347", 
    "doom": "不提供住宿", 
    "extra_hrs": "依工作需要", 
    "food": "提供1餐，每餐扣款金額25", 
    "hire_dur": "不定期契約", 
    "hire_num": "1", 
    "job_desc": "機械繪圖、需會2D及3D、具經驗佳、無經驗肯學習可／週休二日／意者請先電洽或E-mail履歷至saxobrake@yahoo.com.tw白小姐收、無誠勿試(不提供簽名或蓋章服務)／ 徵 機械製圖員", 
    "job_id": "8624699", 
    "job_req": "全職\r\n                            \r\n                            日班：自08時00分至17時00分", 
    "job_title": "機械製圖員", 
    "job_type": "機械製圖員", 
    "off_days": "週休二日", 
    "pay_type": "依學經歷、證照核薪", 
    "work_exp": "不拘", 
    "work_loc": "工作地非屬專區"
}