{
    "ac_deg": "不拘", 
    "ac_dep": "不拘", 
    "ac_sch": "無", 
    "com_addr": "台中市大肚區新興里沙田路二段１３２巷４８號", 
    "com_name": "合順利興業股份有限公司", 
    "com_unicode": "55682232", 
    "doom": "提供住宿，月扣金額2120", 
    "extra_hrs": "依工作需要", 
    "food": "提供2餐，每餐扣款金額60", 
    "hire_dur": "不定期契約", 
    "hire_num": "3", 
    "job_desc": "操作出料機，剖台，燒台和裁斷機等機器設備/面試時間:每週一.三.五上午08:00-12:00", 
    "job_id": "8638583", 
    "job_req": "全職\r\n                            \r\n                            日班：自08時00分至17時00分", 
    "job_title": "操作工", 
    "job_type": "其它機械操作工", 
    "off_days": "依公司規定(月休8天)", 
    "pay_type": "月薪\r\n                            \r\n                            24000 - 28560", 
    "work_exp": "不拘", 
    "work_loc": "工作地非屬專區"
}