{
    "ac_deg": "專科", 
    "ac_dep": "不拘", 
    "ac_sch": "無", 
    "com_addr": "台北市中山區台北市中山區", 
    "com_name": "三澧企業股份有限公司", 
    "com_unicode": "16098275", 
    "doom": "不提供住宿", 
    "extra_hrs": "", 
    "food": "", 
    "hire_dur": "不定期契約", 
    "hire_num": "2", 
    "job_desc": "1.官方粉絲團、品牌官網經營與管理，具備多元品牌整合能力。 2.FB、Instagram等主流社群媒體社群操作，活動規劃、執行、效益分析。 3.議題操作與創意提案產出，擅長行銷創意發想，文案撰寫，圖文編輯，微電影、影片影音剪輯。 4.評估行銷活動業績達成率與成效追蹤分析，並進行後續企劃調整 。 5.具備與個百貨商場各檔期活動對接、執行相關經驗。", 
    "job_id": "8648911", 
    "job_req": "全職\r\n                            \r\n                            日班", 
    "job_title": "百貨行銷企劃「本職缺勿開介紹卡」", 
    "job_type": "行銷企劃人員", 
    "off_days": "週休二日", 
    "pay_type": "依學經歷、證照核薪", 
    "work_exp": "5年以上工作經驗", 
    "work_loc": "工作地非屬專區"
}