{
    "ac_deg": "不拘", 
    "ac_dep": "不拘", 
    "ac_sch": "無", 
    "com_addr": "台南市新營區信義街６１之３號", 
    "com_name": "允泰護理之家", 
    "com_unicode": "36721333", 
    "doom": "提供住宿，月扣金額2500", 
    "extra_hrs": "依工作需要", 
    "food": "提供2餐，每餐扣款金額50", 
    "hire_dur": "不定期契約", 
    "hire_num": "6", 
    "job_desc": "照顧年長及身心障礙者；輪三班，08:00~18:00(中間休息2H)，16:00~24:00，24:00~08:00；供膳宿，住宿月扣2500元，供2餐每餐扣50元。需有照顧服務員證照或取得相關受訓時數證明", 
    "job_id": "8650807", 
    "job_req": "全職\r\n                            \r\n                            日班：自08時00分至18時00分、中班：自16時00分至00時00分、夜班：自00時00分至08時00分", 
    "job_title": "機構看護工(符合缺工獎勵)", 
    "job_type": "看護人員", 
    "off_days": "排休(1個月休8日)", 
    "pay_type": "月薪\r\n                            \r\n                            27500 - 27500", 
    "work_exp": "不拘", 
    "work_loc": "工作地非屬專區"
}