{
    "ac_deg": "高職", 
    "ac_dep": "不拘", 
    "ac_sch": "無", 
    "com_addr": "高雄市楠梓區大學七街２３６號１，２樓", 
    "com_name": "凱莉都汽車旅館", 
    "com_unicode": "08903305", 
    "doom": "不提供住宿", 
    "extra_hrs": "", 
    "food": "", 
    "hire_dur": "不定期契約", 
    "hire_num": "2", 
    "job_desc": "徵:代班櫃檯服務人員-服務熱忱.細心，意者攜履歷親洽。", 
    "job_id": "8658495", 
    "job_req": "全職\r\n                            \r\n                            日班、夜班", 
    "job_title": "代班櫃檯服務人員", 
    "job_type": "櫃檯服務人員", 
    "off_days": "依公司規定(.)", 
    "pay_type": "依學經歷、證照核薪", 
    "work_exp": "不拘", 
    "work_loc": "工作地非屬專區"
}