{
    "ac_deg": "不拘", 
    "ac_dep": "不拘", 
    "ac_sch": "無", 
    "com_addr": "高雄市大寮區農場路２０３號", 
    "com_name": "亞冠冷凍機械股份有限公司", 
    "com_unicode": "23355572", 
    "doom": "不提供住宿", 
    "extra_hrs": "", 
    "food": "", 
    "hire_dur": "不定期契約", 
    "hire_num": "2", 
    "job_desc": "徵:倉管人員(請先MAIL履歷或電洽)工作內容:1.以有條理且易取得的方式存放倉庫中的貨品、控管供需及安全庫存量。 2.進出貨管理作業。 3.定期存貨盤點。 4.安排出貨管理及統計。 5.協助生產作業流程(備料予生產部門)。 6.倉庫的整潔及維護。", 
    "job_id": "8659809", 
    "job_req": "全職\r\n                            \r\n                            日班", 
    "job_title": "倉管人員(請先MAIL履歷)", 
    "job_type": "倉管人員", 
    "off_days": "週休二日", 
    "pay_type": "依學經歷、證照核薪", 
    "work_exp": "1年以上工作經驗", 
    "work_loc": "工作地非屬專區"
}