{
    "ac_deg": "大學", 
    "ac_dep": "不拘", 
    "ac_sch": "無", 
    "com_addr": "新北市板橋區新府路１２８號２樓", 
    "com_name": "台灣大食代餐飲有限公司", 
    "com_unicode": "53216578", 
    "doom": "不提供住宿", 
    "extra_hrs": "依工作需要", 
    "food": "", 
    "hire_dur": "不定期契約", 
    "hire_num": "5", 
    "job_desc": "1.賣場營運管理及活動執行。 2.協助檔期活動與企劃。 3.招商與開發新廠商。 4.數據管理及報表製作。 5.商場設備維護管理。 6.其他交辦事項。", 
    "job_id": "8659969", 
    "job_req": "全職\r\n                            \r\n                            日班、中班、夜班", 
    "job_title": "大食代餐飲集團營業部【板橋店】- 樓管(儲備幹部)", 
    "job_type": "儲備幹部", 
    "off_days": "依公司規定(本職缺符合勞動基準法工時及休假等相關規定)", 
    "pay_type": "依學經歷、證照核薪", 
    "work_exp": "不拘", 
    "work_loc": "工作地非屬專區"
}