{
    "ac_deg": "高中", 
    "ac_dep": "不拘", 
    "ac_sch": "無", 
    "com_addr": "基隆市安樂區武隆街６７號", 
    "com_name": "蔚藍海岸實業有限公司", 
    "com_unicode": "80464852", 
    "doom": "不提供住宿", 
    "extra_hrs": "", 
    "food": "", 
    "hire_dur": "不定期契約", 
    "hire_num": "3", 
    "job_desc": "1.對進房之顧客進行結帳 2.接受訂位或者是訂房並記錄 3.接待顧客，安排訂房 4.回答有關費用，住宿時間，觀光等相關服務問題 5.為旅客回答房內設備使用說明 6.安排行李搬運、叫車等服務 7.在公司時間九小時月休八天", 
    "job_id": "8660493", 
    "job_req": "全職\r\n                            \r\n                            日班：自06時30分至15時30分、中班：自14時30分至23時30分、夜班：自22時00分至07時30分、輪班三班制", 
    "job_title": "櫃檯服務人員", 
    "job_type": "櫃檯服務人員", 
    "off_days": "排休(1個月休8日)", 
    "pay_type": "依學經歷、證照核薪", 
    "work_exp": "不拘", 
    "work_loc": "工作地非屬專區"
}