{
    "ac_deg": "高職", 
    "ac_dep": "不拘", 
    "ac_sch": "無", 
    "com_addr": "桃園市楊梅區幼一廠:楊梅區獅二路1號", 
    "com_name": "地球綜合工業股份有限公司", 
    "com_unicode": "07147916", 
    "doom": "不提供住宿", 
    "extra_hrs": "", 
    "food": "", 
    "hire_dur": "不定期契約", 
    "hire_num": "2", 
    "job_desc": "1.備鍋爐操作證照，無經驗可。 2.蒸器鍋爐/熱媒鍋爐/燃燒爐/空壓機操作及溶劑回收作業。 3.須輪班。", 
    "job_id": "8593871", 
    "job_req": "全職\r\n                            \r\n                            輪班二班制、輪班三班制", 
    "job_title": "鍋爐技術員", 
    "job_type": "蒸汽引擎及鍋爐操作工", 
    "off_days": "週休二日", 
    "pay_type": "依學經歷、證照核薪", 
    "work_exp": "不拘", 
    "work_loc": "工作地非屬專區"
}