{
    "ac_deg": "大學", 
    "ac_dep": "不拘", 
    "ac_sch": "無", 
    "com_addr": "台北市中正區、新北市巨匠美語分校", 
    "com_name": "巨匠電腦股份有限公司", 
    "com_unicode": "12653785", 
    "doom": "不提供住宿", 
    "extra_hrs": "", 
    "food": "", 
    "hire_dur": "不定期契約", 
    "hire_num": "5", 
    "job_desc": "1.美語課程規劃服務、櫃台招生業務。2.可配合輪早晚班及階段性跨區轉調(縣市)培訓者。3.歷練基層職務後轉門市店長職。", 
    "job_id": "8626069", 
    "job_req": "全職\r\n                            \r\n                            日班：自09時30分至19時30分、中班：自13時30分至22時00分", 
    "job_title": "美語課程儲備店長", 
    "job_type": "儲備幹部", 
    "off_days": "依公司規定(.)", 
    "pay_type": "月薪\r\n                            \r\n                            30000 - 35000", 
    "work_exp": "不拘", 
    "work_loc": "工作地非屬專區"
}