{
    "ac_deg": "高中", 
    "ac_dep": "不拘", 
    "ac_sch": "無", 
    "com_addr": "新北市林口區仁愛路一段６３９號", 
    "com_name": "何迪企業股份有限公司", 
    "com_unicode": "23776861", 
    "doom": "不提供住宿", 
    "extra_hrs": "依工作需要", 
    "food": "", 
    "hire_dur": "不定期契約", 
    "hire_num": "1", 
    "job_desc": "人事文書管理 岀貨交期回覆 訂單交期回覆 主管交辦事項 基本會計事項", 
    "job_id": "3746592", 
    "job_req": "全職\r\n                            \r\n                            日班：自08時00分至17時00分", 
    "job_title": "一般會計及出納", 
    "job_type": "一般會計及出納", 
    "off_days": "週休二日", 
    "pay_type": "依學經歷、證照核薪", 
    "work_exp": "1年以上工作經驗", 
    "work_loc": "工作地非屬專區"
}