{
    "ac_deg": "不拘", 
    "ac_dep": "不拘", 
    "ac_sch": "無", 
    "com_addr": "新北市新莊區中央路469號", 
    "com_name": "典華婚訂資源整合股份有限公司", 
    "com_unicode": "27530072", 
    "doom": "不提供住宿", 
    "extra_hrs": "依工作需要", 
    "food": "", 
    "hire_dur": "不定期契約", 
    "hire_num": "5", 
    "job_desc": "1.負責餐具和器皿碗盤清洗。 2.廚房器具清洗。 3.工作環境整理。", 
    "job_id": "7908709", 
    "job_req": "全職\r\n                            \r\n                            輪班三班制", 
    "job_title": "華亭聚中餐廳(新莊)-洗碗人員", 
    "job_type": "廚務清潔員", 
    "off_days": "排休(1個月休8日)", 
    "pay_type": "月薪\r\n                            \r\n                            24000 - 27000", 
    "work_exp": "不拘", 
    "work_loc": "工作地非屬專區"
}