{
    "ac_deg": "大學", 
    "ac_dep": "不拘", 
    "ac_sch": "無", 
    "com_addr": "新竹市東區光復路二段2巷53號3樓", 
    "com_name": "智禾科技股份有限公司", 
    "com_unicode": "80315426", 
    "doom": "不提供住宿", 
    "extra_hrs": "", 
    "food": "", 
    "hire_dur": "不定期契約", 
    "hire_num": "3", 
    "job_desc": "1.新專案之網頁設計、維護。 2.專案之資料庫設計/管理/程式撰寫。 3.既有程式與資料庫之維護。 4.熟悉Visual Studio開發環境者佳", 
    "job_id": "8576223", 
    "job_req": "全職\r\n                            \r\n                            日班：自08時30分至18時00分", 
    "job_title": "網頁程式工程師", 
    "job_type": "Internet程式設計師", 
    "off_days": "週休二日", 
    "pay_type": "依學經歷、證照核薪", 
    "work_exp": "1年以上工作經驗", 
    "work_loc": "工作地非屬專區"
}