{
    "ac_deg": "大學", 
    "ac_dep": "機械工程(學)系", 
    "ac_sch": "無", 
    "com_addr": "台中市大里區仁化路２６１號", 
    "com_name": "力山工業股份有限公司", 
    "com_unicode": "55759180", 
    "doom": "不提供住宿", 
    "extra_hrs": "依工作需要", 
    "food": "提供1餐，每餐扣款金額", 
    "hire_dur": "不定期契約", 
    "hire_num": "1", 
    "job_desc": "1、具機械相關產業品保主管工作經驗者。 2、負責ISO體制之推行、供應商IQC管理，以及製品IPQC及OQC管理。 3 、具品保統計分析能力 4、外語能力佳意者請先行電洽約面試時間/無誠勿試(不提供簽名或蓋章服務) / 徵 品管主管", 
    "job_id": "8578871", 
    "job_req": "全職\r\n                            \r\n                            日班", 
    "job_title": "品管主管", 
    "job_type": "品管/品保主管", 
    "off_days": "週休二日", 
    "pay_type": "依學經歷、證照核薪", 
    "work_exp": "需具備「機械工程管理經驗」，5年以上工作經驗", 
    "work_loc": "工作地非屬專區"
}