{
    "ac_deg": "不拘", 
    "ac_dep": "不拘", 
    "ac_sch": "無", 
    "com_addr": "台北市中山區北安路６２１巷６弄２３號", 
    "com_name": "大明食堂", 
    "com_unicode": "26368614", 
    "doom": "不提供住宿", 
    "extra_hrs": "", 
    "food": "提供1餐，每餐扣款金額0", 
    "hire_dur": "不定期契約", 
    "hire_num": "2", 
    "job_desc": "內、外場餐飲服務工作", 
    "job_id": "8585935", 
    "job_req": "兼職\r\n                            \r\n                            部份工時：自11時00分至14時30分、自17時00分至21時30分", 
    "job_title": "內、外場餐飲服務生", 
    "job_type": "餐飲服務及接待員", 
    "off_days": "排休(1個月休8日)", 
    "pay_type": "時薪\r\n                            \r\n                            150 - 160", 
    "work_exp": "不拘", 
    "work_loc": "工作地非屬專區"
}