{
    "ac_deg": "不拘", 
    "ac_dep": "不拘", 
    "ac_sch": "無", 
    "com_addr": "新竹市公園路216巷16號新竹物流", 
    "com_name": "信林企業股份有限公司", 
    "com_unicode": "70473229", 
    "doom": "不提供住宿", 
    "extra_hrs": "依工作需要", 
    "food": "", 
    "hire_dur": "不定期契約", 
    "hire_num": "5", 
    "job_desc": "理貨人員 (新竹所)，工作內容：貨物整理分類/上貨下貨/堆疊貨物(需搬重物)工作時間：大夜班，00:30-07:00若有意應徵，請於每日15:00後致電0955-186990李先生預約面試，無誠勿擾。", 
    "job_id": "8588827", 
    "job_req": "全職\r\n                            \r\n                            日班：自00時30分至07時00分", 
    "job_title": "【新竹所】理貨人員(以電話預約面試，無誠勿擾)", 
    "job_type": "倉管人員", 
    "off_days": "依公司規定(排班)", 
    "pay_type": "依學經歷、證照核薪", 
    "work_exp": "不拘", 
    "work_loc": "工作地非屬專區"
}