{
    "ac_deg": "專科", 
    "ac_dep": "會計學類", 
    "ac_sch": "無", 
    "com_addr": "高雄市左營區華夏路1062號", 
    "com_name": "濃庄茶館股份有限公司(美濃客家菜)", 
    "com_unicode": "80376128", 
    "doom": "不提供住宿", 
    "extra_hrs": "", 
    "food": "", 
    "hire_dur": "不定期契約", 
    "hire_num": "1", 
    "job_desc": "徵：櫃台會計作業人員(大中店) 1.負責接待客人。2.櫃檯收錢。3.簡易會計帳目製作。意者請電洽劉先生約面試時間", 
    "job_id": "8591881", 
    "job_req": "全職\r\n                            \r\n                            日班：自10時00分至14時00分、夜班：自17時00分至21時00分", 
    "job_title": "櫃台會計作業人員(大中店)", 
    "job_type": "一般會計及出納", 
    "off_days": "排休(1個月休8日)", 
    "pay_type": "月薪\r\n                            \r\n                            26000 - 28000", 
    "work_exp": "不拘", 
    "work_loc": "工作地非屬專區"
}