{
    "ac_deg": "高職", 
    "ac_dep": "護理學系", 
    "ac_sch": "無", 
    "com_addr": "台北市內湖區成功路５段４２０巷２６號", 
    "com_name": "康寧醫療財團法人", 
    "com_unicode": "92025801", 
    "doom": "不提供住宿", 
    "extra_hrs": "", 
    "food": "", 
    "hire_dur": "不定期契約(長期僱用)", 
    "hire_num": "8", 
    "job_desc": "居家護理、病房、護理之家、家護病房之護理照護工作。", 
    "job_id": "8596921", 
    "job_req": "全職\r\n                            \r\n                            輪班三班制", 
    "job_title": "不分科護理師", 
    "job_type": "護士", 
    "off_days": "依公司規定(依公司規定)", 
    "pay_type": "依學經歷、證照核薪", 
    "work_exp": "需具備「臨床護理照護」，1年以上工作經驗", 
    "work_loc": "工作地非屬專區"
}