{
    "ac_deg": "不拘", 
    "ac_dep": "不拘", 
    "ac_sch": "無", 
    "com_addr": "高雄市鳥松區仁美里美山路１９巷１７號", 
    "com_name": "冠勝鋁模股份有限公司", 
    "com_unicode": "84858983", 
    "doom": "不提供住宿", 
    "extra_hrs": "", 
    "food": "", 
    "hire_dur": "不定期契約", 
    "hire_num": "2", 
    "job_desc": "徵:行政業務助理工作內容:1.協助客戶對於商品價格的查詢及報價相關的問題 2.負責部門相關文件之整理，建檔以及追蹤，於有效時間內回覆顧客信件 3.出貨單、訂單之處理及整理 4.出、進貨點收料", 
    "job_id": "8618061", 
    "job_req": "全職\r\n                            \r\n                            日班：自08時00分至17時00分", 
    "job_title": "行政業務助理", 
    "job_type": "行政助理", 
    "off_days": "依公司規定(符合勞動基準法工時)", 
    "pay_type": "依學經歷、證照核薪", 
    "work_exp": "需具備「行政」，1年以上工作經驗", 
    "work_loc": "工作地非屬專區"
}