{
    "ac_deg": "專科", 
    "ac_dep": "不拘", 
    "ac_sch": "無", 
    "com_addr": "新竹縣竹北市成功十街138號", 
    "com_name": "新竹市私立米羅幼兒園", 
    "com_unicode": "99503861", 
    "doom": "不提供住宿", 
    "extra_hrs": "依工作需要", 
    "food": "提供1餐，每餐扣款金額", 
    "hire_dur": "不定期契約", 
    "hire_num": "5", 
    "job_desc": "幼教帶班工作經驗1年以上供午餐,午休時間1H。其他條件：***需具有教保員執照或合格幼教師為佳 ***配合度高工作認真勤奮願意與人溝通協調配合排班", 
    "job_id": "8618069", 
    "job_req": "全職\r\n                            \r\n                            日班：自07時30分至17時00分、中班：自08時30分至18時00分、輪班二班制", 
    "job_title": "幼教老師/教保員(幼幼、小、中、大班)", 
    "job_type": "幼教老師", 
    "off_days": "週休二日", 
    "pay_type": "依學經歷、證照核薪", 
    "work_exp": "不拘", 
    "work_loc": "工作地非屬專區"
}