{
    "ac_deg": "高中", 
    "ac_dep": "不拘", 
    "ac_sch": "無", 
    "com_addr": "高雄市仁武區.", 
    "com_name": "美日欣有限公司", 
    "com_unicode": "86462557", 
    "doom": "不提供住宿", 
    "extra_hrs": "依工作需要", 
    "food": "", 
    "hire_dur": "不定期契約", 
    "hire_num": "3", 
    "job_desc": "徵:高屏地區業務人員＜一般市場＞ -本職缺屬外勤業務性質，專攻高雄、屏東地區之一般通路市場，適合個性外向、開朗、不怕生，愛與人互動的朋友，男女均可，試用期後依照個人特質及意願分配區域。 意者請電洽李小姐約面試時間", 
    "job_id": "8619337", 
    "job_req": "全職\r\n                            \r\n                            日班", 
    "job_title": "高屏地區業務人員＜一般市場＞", 
    "job_type": "業務人員", 
    "off_days": "週休二日", 
    "pay_type": "月薪\r\n                            \r\n                            30000 - 30000", 
    "work_exp": "不拘", 
    "work_loc": "工作地非屬專區"
}