{
    "ac_deg": "專科", 
    "ac_dep": "護理學系", 
    "ac_sch": "無", 
    "com_addr": "台中市北屯區松竹南街６號", 
    "com_name": "華穗護理之家", 
    "com_unicode": "19286048", 
    "doom": "不提供住宿", 
    "extra_hrs": "依工作需要", 
    "food": "", 
    "hire_dur": "不定期契約", 
    "hire_num": "2", 
    "job_desc": "執行護理業務、擬定護理計畫、執行醫囑、填寫紀錄/周休二日/月薪33000-45000/無誠勿試(不提供簽名蓋章服務)/徵 護理師", 
    "job_id": "8620739", 
    "job_req": "全職\r\n                            \r\n                            日班、中班、夜班、輪班三班制", 
    "job_title": "護理師", 
    "job_type": "專科護理師", 
    "off_days": "週休二日", 
    "pay_type": "月薪\r\n                            \r\n                            33000 - 45000", 
    "work_exp": "不拘", 
    "work_loc": "工作地非屬專區"
}