{
    "ac_deg": "國小", 
    "ac_dep": "不拘", 
    "ac_sch": "無", 
    "com_addr": "新北市新店區安康路三段５２７號", 
    "com_name": "中國銲條機械股份有限公司", 
    "com_unicode": "03090005", 
    "doom": "不提供住宿", 
    "extra_hrs": "", 
    "food": "", 
    "hire_dur": "不定期契約", 
    "hire_num": "2", 
    "job_desc": "接受製程工程師之指導，從事產品適當生產作業順序及時間配置等技術工作。傳統製造業工廠，產品沉重,工作環境差、歡迎吃苦耐勞、肯學習人士加入本公司。會操作堆高機尤佳。", 
    "job_id": "8621085", 
    "job_req": "全職\r\n                            \r\n                            日班：自08時00分至17時00分", 
    "job_title": "技術員", 
    "job_type": "製程技術員", 
    "off_days": "週休二日", 
    "pay_type": "月薪\r\n                            \r\n                            25000 - 30000", 
    "work_exp": "不拘", 
    "work_loc": "工作地非屬專區"
}