{
    "ac_deg": "不拘", 
    "ac_dep": "不拘", 
    "ac_sch": "無", 
    "com_addr": "高雄市大樹區統嶺里信誼路1號(信誼高爾夫球場)", 
    "com_name": "日盛發有限公司", 
    "com_unicode": "89266811", 
    "doom": "不提供住宿", 
    "extra_hrs": "依工作需要", 
    "food": "", 
    "hire_dur": "不定期契約", 
    "hire_num": "1", 
    "job_desc": "清潔人員-清潔整理駐點清潔信誼高爾夫球場(請先電洽約面試時間)", 
    "job_id": "8626393", 
    "job_req": "全職\r\n                            \r\n                            日班：自08時00分至17時00分", 
    "job_title": "清潔人員", 
    "job_type": "環境清潔工", 
    "off_days": "依公司規定(依公司規定)", 
    "pay_type": "依學經歷、證照核薪", 
    "work_exp": "不拘", 
    "work_loc": "工作地非屬專區"
}