{
    "ac_deg": "高職", 
    "ac_dep": "不拘", 
    "ac_sch": "無", 
    "com_addr": "高雄市左營區新榮街85號", 
    "com_name": "皇家特勤保全股份有限公司", 
    "com_unicode": "28600618", 
    "doom": "不提供住宿", 
    "extra_hrs": "依工作需要", 
    "food": "", 
    "hire_dur": "不定期契約", 
    "hire_num": "3", 
    "job_desc": "急徵：豪宅禮賓保全  1.門禁管制，巡邏，維護安全 2.系統監看 3.事故處理 3.禮賓接待 月薪  34,000 至 36,000 元 月休8天 意者請電洽劉經理約面試時間", 
    "job_id": "8627837", 
    "job_req": "全職\r\n                            \r\n                            日班、夜班、輪班二班制", 
    "job_title": "急徵：豪宅禮賓保全", 
    "job_type": "保全人員", 
    "off_days": "排休(1個月休8日)", 
    "pay_type": "月薪\r\n                            \r\n                            34000 - 36000", 
    "work_exp": "不拘", 
    "work_loc": "工作地非屬專區"
}