{
    "ac_deg": "高中", 
    "ac_dep": "不拘", 
    "ac_sch": "無", 
    "com_addr": "新竹市香山區埔前路４９號", 
    "com_name": "華夏玻璃股份有限公司", 
    "com_unicode": "47109348", 
    "doom": "提供住宿，月扣金額", 
    "extra_hrs": "依工作需要", 
    "food": "", 
    "hire_dur": "不定期契約", 
    "hire_num": "5", 
    "job_desc": "\"1.觀察機械的運作情形，偵測設備不足處或機械故障處，必要時須進行調整。2.檢查機械零件不足處，以確定機械操作的準確性。3.生產設備維護、保養及維修並預防問題發生。\"", 
    "job_id": "8627927", 
    "job_req": "全職\r\n                            \r\n                            日班：自08時00分至16時00分、中班：自16時00分至00時00分、夜班：自00時00分至08時00分、輪班三班制", 
    "job_title": "機械設備裝修員(缺工獎勵)", 
    "job_type": "其它機械操作工", 
    "off_days": "依公司規定(排班月休8日)", 
    "pay_type": "月薪\r\n                            \r\n                            26000 - 34500", 
    "work_exp": "不拘", 
    "work_loc": "工作地非屬專區"
}