{
    "ac_deg": "不拘", 
    "ac_dep": "不拘", 
    "ac_sch": "無", 
    "com_addr": "桃園市楊梅區裕成南路１５９號", 
    "com_name": "楊梅佳醫護理之家", 
    "com_unicode": "82209626", 
    "doom": "不提供住宿", 
    "extra_hrs": "依工作需要", 
    "food": "提供1餐，每餐扣款金額", 
    "hire_dur": "不定期契約", 
    "hire_num": "2", 
    "job_desc": "1.三餐膳食準備及製作。2.食材叫貨、進貨、備料、盤點、確保食品衛生安全。3.廚房環境清潔。4.具備中餐丙級技術士以上資格，優先錄用", 
    "job_id": "8630073", 
    "job_req": "全職\r\n                            \r\n                            日班：自08時30分至18時30分", 
    "job_title": "中/西餐烹飪廚師", 
    "job_type": "中/西餐烹飪廚師", 
    "off_days": "依公司規定(遵循法規(排休))", 
    "pay_type": "依學經歷、證照核薪", 
    "work_exp": "不拘", 
    "work_loc": "工作地非屬專區"
}