{
    "ac_deg": "高職", 
    "ac_dep": "餐飲管理科", 
    "ac_sch": "無", 
    "com_addr": "台北市中山區中山北路1段", 
    "com_name": "台灣瑪拉斯藝品有限公司", 
    "com_unicode": "16285798", 
    "doom": "不提供住宿", 
    "extra_hrs": "", 
    "food": "提供1餐，每餐扣款金額80", 
    "hire_dur": "不定期契約", 
    "hire_num": "1", 
    "job_desc": "負責餐飲場所的內外場聯繫、顧客菜單諮詢、點餐供餐及桌面環境清潔。", 
    "job_id": "8632795", 
    "job_req": "全職\r\n                            \r\n                            日班：自11時00分至20時00分", 
    "job_title": "長期假日工讀生-服務人員", 
    "job_type": "餐飲服務及接待員", 
    "off_days": "依公司規定(每周休假1日)", 
    "pay_type": "時薪\r\n                            \r\n                            140 - 140", 
    "work_exp": "需具備「餐飲」，1年內工作經驗", 
    "work_loc": "工作地非屬專區"
}