{
    "ac_deg": "專科", 
    "ac_dep": "不拘", 
    "ac_sch": "無", 
    "com_addr": "台北市松山區虎林街232巷36號4樓", 
    "com_name": "盛世商業顧問有限公司", 
    "com_unicode": "54684584", 
    "doom": "不提供住宿", 
    "extra_hrs": "不需加班", 
    "food": "", 
    "hire_dur": "不定期契約", 
    "hire_num": "2", 
    "job_desc": "從事稅收、買賣契約及其他證件之登錄與核算，以決定個人、企業應繳之稅務種類及其他金額等工作。", 
    "job_id": "8637749", 
    "job_req": "全職\r\n                            \r\n                            日班：自08時30分至17時30分", 
    "job_title": "會計人員", 
    "job_type": "稅務人員", 
    "off_days": "週休二日", 
    "pay_type": "月薪\r\n                            \r\n                            27000 - 30000", 
    "work_exp": "需具備「會計人員」，1年以上工作經驗", 
    "work_loc": "工作地非屬專區"
}