{
    "ac_deg": "不拘", 
    "ac_dep": "不拘", 
    "ac_sch": "無", 
    "com_addr": "桃園市龍潭區", 
    "com_name": "昊麒國際有限公司", 
    "com_unicode": "42594237", 
    "doom": "不提供住宿", 
    "extra_hrs": "依工作需要", 
    "food": "提供1餐，每餐扣款金額0", 
    "hire_dur": "不定期契約", 
    "hire_num": "2", 
    "job_desc": "1.依照設計工程師草圖及規格，從事繪製機械、機具及有關機件之工作圖等工作.2.進行機械設計並輸出設計文件( 機器圖紙、外購件清單、機器操作說明書等)3.協助機器製造、安裝等後續工作，並與相關部門做溝通.4.針對測試有誤之設計不良原因做調整改善.5.改良舊機台或設計新機台以適應新產品之生產需求.6.學習市場新技術並適時將新技術引進企業.7.會使用Solid Works 3D及2D軟體.8.協助廠內事務處理.", 
    "job_id": "8642127", 
    "job_req": "全職\r\n                            \r\n                            日班：自08時00分至17時20分", 
    "job_title": "電腦繪圖設計人員", 
    "job_type": "機械製圖員", 
    "off_days": "週休二日", 
    "pay_type": "月薪\r\n                            \r\n                            27000 - 40000", 
    "work_exp": "1年以上工作經驗", 
    "work_loc": "工作地非屬專區"
}