{
    "ac_deg": "高職", 
    "ac_dep": "不拘", 
    "ac_sch": "無", 
    "com_addr": "台中市潭子區", 
    "com_name": "金富山精密工業有限公司", 
    "com_unicode": "84426613", 
    "doom": "不提供住宿", 
    "extra_hrs": "依工作需要", 
    "food": "提供1餐，每餐扣款金額0", 
    "hire_dur": "不定期契約", 
    "hire_num": "2", 
    "job_desc": "負責規劃配置由原料接收至成品出廠，全部過程之機器設備，使空間配置適切，並定期設備檢查。*協助管理生產流程、控制工件尺寸及品質、加工現場安全監管*車床操作機器設備之保養與維護", 
    "job_id": "8647983", 
    "job_req": "全職\r\n                            \r\n                            日班：自08時00分至17時00分", 
    "job_title": "CNC車床技術人員", 
    "job_type": "生產設備工程師", 
    "off_days": "週休二日", 
    "pay_type": "月薪\r\n                            \r\n                            24000 - 60000", 
    "work_exp": "不拘", 
    "work_loc": "工作地非屬專區"
}