{
    "ac_deg": "不拘", 
    "ac_dep": "不拘", 
    "ac_sch": "無", 
    "com_addr": "新北市深坑區北深路三段57號", 
    "com_name": "大氣層事業有限公司", 
    "com_unicode": "97446561", 
    "doom": "不提供住宿", 
    "extra_hrs": "", 
    "food": "", 
    "hire_dur": "不定期契約", 
    "hire_num": "3", 
    "job_desc": "需會使用工業針車。車縫組合、生產製作，充氣造型廣告物，充氣裝置藝術。歡迎加入我們的製作團隊！！！", 
    "job_id": "8411937", 
    "job_req": "全職\r\n                            \r\n                            日班：自09時00分至18時30分", 
    "job_title": "平車人員", 
    "job_type": "車縫／裁縫類人員", 
    "off_days": "週休二日", 
    "pay_type": "月薪\r\n                            \r\n                            30000 - 50000", 
    "work_exp": "不拘", 
    "work_loc": "工作地非屬專區"
}