{
    "ac_deg": "專科", 
    "ac_dep": "教育學類", 
    "ac_sch": "無", 
    "com_addr": "高雄市小港區漢民路７３５號(臨海工業區)", 
    "com_name": "高雄市私立子信幼稚園", 
    "com_unicode": "15561802", 
    "doom": "不提供住宿", 
    "extra_hrs": "依工作需要", 
    "food": "", 
    "hire_dur": "不定期契約", 
    "hire_num": "2", 
    "job_desc": "1.協助孩童完成當天功課，並注意寫字的工整。 2.指導國小學生課業，如：幫孩童複習國語、數學、自然等。 3.輔導學生行為，校正不良生活習慣、衛生習慣，如：東西用畢需歸位、有禮貌的溝通、保持座位附近的清潔等。 4.調解孩童間的爭吵，並協助孩童建立良好的人際關係。 5.傾聽孩子的心聲並給予關懷鼓勵。", 
    "job_id": "8590969", 
    "job_req": "全職\r\n                            \r\n                            日班：自10時00分至19時00分", 
    "job_title": "安親班老師", 
    "job_type": "幼教老師", 
    "off_days": "週休二日", 
    "pay_type": "依學經歷、證照核薪", 
    "work_exp": "1年以上工作經驗", 
    "work_loc": "工作地非屬專區"
}