{
    "ac_deg": "高中", 
    "ac_dep": "不拘", 
    "ac_sch": "無", 
    "com_addr": "新北市新莊區中華路２段９號９樓", 
    "com_name": "春井有限公司", 
    "com_unicode": "67074374", 
    "doom": "不提供住宿", 
    "extra_hrs": "", 
    "food": "", 
    "hire_dur": "不定期契約", 
    "hire_num": "5", 
    "job_desc": "1.勿須開發客戶2.負責健康課程宣教,產品,介紹,推銷3.需自備汽車(有交通補貼)4.有消防,健康器材講師男女不拘有經驗尤佳5.上班地點:北.中.南區**請先投遞履歷約面試-walle046@yahoo.com.tw***", 
    "job_id": "8596797", 
    "job_req": "全職\r\n                            \r\n                            日班", 
    "job_title": "業務講師(謝絕蓋章)", 
    "job_type": "業務人員", 
    "off_days": "依公司規定(週休二日)", 
    "pay_type": "月薪\r\n                            \r\n                            46000 - 60000", 
    "work_exp": "1年以上工作經驗", 
    "work_loc": "工作地非屬專區"
}