{
    "ac_deg": "不拘", 
    "ac_dep": "不拘", 
    "ac_sch": "無", 
    "com_addr": "台中市沙鹿區台灣大道六段２５９號", 
    "com_name": "全國加油站股份有限公司中港路加油站", 
    "com_unicode": "81973117", 
    "doom": "不提供住宿", 
    "extra_hrs": "", 
    "food": "", 
    "hire_dur": "不定期契約", 
    "hire_num": "5", 
    "job_desc": "1.服務加油、服務洗車。 2.表現良好可升為正職員工(月薪)。", 
    "job_id": "8600013", 
    "job_req": "全職\r\n                            \r\n                            日班：自06時50分至15時00分、中班：自14時50分至23時00分", 
    "job_title": "時薪加油服務員", 
    "job_type": "加油服務生", 
    "off_days": "排休(1個月休8日)", 
    "pay_type": "時薪\r\n                            \r\n                            140 - 150", 
    "work_exp": "不拘", 
    "work_loc": "工作地非屬專區"
}