{
    "ac_deg": "高職", 
    "ac_dep": "不拘", 
    "ac_sch": "無", 
    "com_addr": "高雄市左營區自由二路309號3F", 
    "com_name": "財團法人弘道老人福利基金會", 
    "com_unicode": "98179269", 
    "doom": "不提供住宿", 
    "extra_hrs": "", 
    "food": "", 
    "hire_dur": "不定期契約", 
    "hire_num": "3", 
    "job_desc": "徵：照顧助理 (工作項目：陪伴、沐浴、備餐、家務清潔、肢體關節運動等，日班，月薪22000-26000元，高中職以上畢，具重型機車駕照，需會word、excel、PPT等。)意者請MAIL履歷", 
    "job_id": "8624331", 
    "job_req": "全職\r\n                            \r\n                            日班：自08時00分至17時00分", 
    "job_title": "照顧助理", 
    "job_type": "看護人員", 
    "off_days": "排休(1個月休8日)", 
    "pay_type": "月薪\r\n                            \r\n                            22000 - 26000", 
    "work_exp": "不拘", 
    "work_loc": "工作地非屬專區"
}