{
    "ac_deg": "不拘", 
    "ac_dep": "不拘", 
    "ac_sch": "無", 
    "com_addr": "高雄市大寮區 華西路47號", 
    "com_name": "強言企業有限公司", 
    "com_unicode": "16807353", 
    "doom": "不提供住宿", 
    "extra_hrs": "", 
    "food": "", 
    "hire_dur": "不定期契約", 
    "hire_num": "2", 
    "job_desc": "徵:(機電工程師)地下管線, 油氣儲槽, 鋼筋混凝土結構 防蝕工程附加條件：有工安證照佳", 
    "job_id": "8639783", 
    "job_req": "全職\r\n                            \r\n                            日班：自08時00分至17時00分", 
    "job_title": "機電工程師", 
    "job_type": "微機電工程師", 
    "off_days": "週休二日", 
    "pay_type": "依學經歷、證照核薪", 
    "work_exp": "不拘", 
    "work_loc": "工作地非屬專區"
}