{
    "ac_deg": "高職", 
    "ac_dep": "不拘", 
    "ac_sch": "無", 
    "com_addr": "桃園市蘆竹區南福街210號", 
    "com_name": "民曜有限公司", 
    "com_unicode": "84107239", 
    "doom": "不提供住宿", 
    "extra_hrs": "", 
    "food": "無", 
    "hire_dur": "不定期契約", 
    "hire_num": "1", 
    "job_desc": "本公司主要營業項目有高空作業車與吊車及各式特種車租賃買賣，為機械類產品。1. 管理零用金。2. 應收應付帳款。3. 催收帳款。4. 需跑銀行及郵局。 5. 簡易流水帳業務接洽", 
    "job_id": "8646423", 
    "job_req": "全職\r\n                            \r\n                            日班：自08時00分至17時30分", 
    "job_title": "會計/業務助理", 
    "job_type": "會計助理", 
    "off_days": "週休二日", 
    "pay_type": "依學經歷、證照核薪", 
    "work_exp": "不拘", 
    "work_loc": "工作地非屬專區"
}