{
    "ac_deg": "大學", 
    "ac_dep": "不拘", 
    "ac_sch": "無", 
    "com_addr": "新竹縣湖口鄉勝利村安宅八街99號", 
    "com_name": "廣生科技股份有限公司", 
    "com_unicode": "86710557", 
    "doom": "不提供住宿", 
    "extra_hrs": "依工作需要", 
    "food": "", 
    "hire_dur": "不定期契約", 
    "hire_num": "1", 
    "job_desc": "1.剛開始主要業務為協助公司導入ERP(需有實務操作經驗)2.辦理銀行現金存款、提款、匯款、轉帳作業。3.執行一般現金收付作業。4.核對儲存現金與記錄是否相符合。5.管理零用金異動及撥補作業。6.製作出納科目餘額表、收款日報表、利息收入調節表、銀行存款收支日報表、銀行往來授信明細表等。7.需協助公司製作交予國外原廠的帳務資料", 
    "job_id": "8652251", 
    "job_req": "全職\r\n                            \r\n                            日班：自08時00分至17時00分", 
    "job_title": "財務專員(用E-MIEL履歷應徵)", 
    "job_type": "財務專業人員", 
    "off_days": "週休二日", 
    "pay_type": "依學經歷、證照核薪", 
    "work_exp": "需具備「財務會計」，2年以上工作經驗", 
    "work_loc": "工作地非屬專區"
}